envify/__init__.py
envify/constants.py
envify/errors.py
envify/main.py
envify/models/config.py
envify/utils/load_envs.py
envify/utils/load_yaml.py
envify-1.0.0.dist-info/METADATA
envify-1.0.0.dist-info/WHEEL
envify-1.0.0.dist-info/RECORD
