Metadata-Version: 2.1
Name: envify
Version: 1.0.0
Summary: A friendly enviroment variable parser to describe envs and parse them. This will make documenting environment variables easier.
Author: Victoria Luquet
Author-email: victoria.tewari@gmail.com
Requires-Python: >=3.10,<4.0
Classifier: Programming Language :: Python :: 3
Classifier: Programming Language :: Python :: 3.10
Classifier: Programming Language :: Python :: 3.11
Classifier: Programming Language :: Python :: 3.12
Requires-Dist: pydantic (>=2.7.0,<3.0.0)
Requires-Dist: pytest (>=8.1.1,<9.0.0)
Requires-Dist: python-dotenv (>=1.0.1,<2.0.0)
Requires-Dist: pyyaml (>=6.0.1,<7.0.0)
